jimla/__init__.py
jimla/broom.py
jimla/data.py
jimla/likelihood.py
jimla/models.py
jimla/priors.py
jimla/py.typed
jimla-0.1.8.dist-info/METADATA
jimla-0.1.8.dist-info/WHEEL
jimla-0.1.8.dist-info/licenses/LICENSE
jimla-0.1.8.dist-info/RECORD
