Metadata-Version: 2.4
Name: jimla
Version: 0.1.8
Summary: Bayesian linear regression with variational inference, inspired by R's lm() and broom
Project-URL: Homepage, https://github.com/alexhallam/jimla
Project-URL: Repository, https://github.com/alexhallam/jimla
Project-URL: Documentation, https://github.com/alexhallam/jimla#readme
Project-URL: Bug Tracker, https://github.com/alexhallam/jimla/issues
Author-email: Alex Hallam <alex.hallam@cfacorp.com>
License: MIT
License-File: LICENSE
Keywords: bayesian,jax,machine-learning,polars,regression,statistics
Classifier: Development Status :: 4 - Beta
Classifier: Intended Audience :: Science/Research
Classifier: License :: OSI Approved :: MIT License
Classifier: Operating System :: OS Independent
Classifier: Programming Language :: Python :: 3
Classifier: Programming Language :: Python :: 3.9
Classifier: Programming Language :: Python :: 3.10
Classifier: Programming Language :: Python :: 3.11
Classifier: Programming Language :: Python :: 3.12
Classifier: Programming Language :: Python :: 3.13
Classifier: Topic :: Scientific/Engineering :: Information Analysis
Classifier: Topic :: Scientific/Engineering :: Mathematics
Requires-Python: >=3.9
Requires-Dist: blackjax>=1.2.5
Requires-Dist: fiasto-py>=0.1.5
Requires-Dist: jax>=0.4.0
Requires-Dist: jaxlib>=0.4.0
Requires-Dist: numpy>=1.24.0
Requires-Dist: polars>=1.33.1
Requires-Dist: rich>=13.0.0
Requires-Dist: rpy2>=3.5.0
Requires-Dist: tidy-viewer-py>=0.3.0
Requires-Dist: wayne-trade>=0.1.5
Provides-Extra: test
Requires-Dist: pytest-cov>=4.0.0; extra == 'test'
Requires-Dist: pytest>=7.0.0; extra == 'test'
